el1xr_opt/__init__.py
el1xr_opt/__main__.py
el1xr_opt/el1xr_Main.py
el1xr_opt/Grid1/Master_InputData_Grid1.xlsm
el1xr_opt/Grid1/oM_Data_Duration_Grid1.csv
el1xr_opt/Grid1/oM_Data_ElectricityDemand_Grid1.csv
el1xr_opt/Grid1/oM_Data_ElectricityGeneration_Grid1.csv
el1xr_opt/Grid1/oM_Data_ElectricityNetwork_Grid1.csv
el1xr_opt/Grid1/oM_Data_ElectricityRetail_Grid1.csv
el1xr_opt/Grid1/oM_Data_HydrogenDemand_Grid1.csv
el1xr_opt/Grid1/oM_Data_HydrogenGeneration_Grid1.csv
el1xr_opt/Grid1/oM_Data_HydrogenNetwork_Grid1.csv
el1xr_opt/Grid1/oM_Data_HydrogenRetail_Grid1.csv
el1xr_opt/Grid1/oM_Data_NodeLocation_Grid1.csv
el1xr_opt/Grid1/oM_Data_OperatingReserveActivation_Grid1.csv
el1xr_opt/Grid1/oM_Data_OperatingReservePrice_Grid1.csv
el1xr_opt/Grid1/oM_Data_OperatingReserveRequire_Grid1.csv
el1xr_opt/Grid1/oM_Data_Option_Grid1.csv
el1xr_opt/Grid1/oM_Data_Parameter_Grid1.csv
el1xr_opt/Grid1/oM_Data_Period_Grid1.csv
el1xr_opt/Grid1/oM_Data_Scenario_Grid1.csv
el1xr_opt/Grid1/oM_Data_Tariff_Grid1.csv
el1xr_opt/Grid1/oM_Data_VarEnergyCost_Grid1.csv
el1xr_opt/Grid1/oM_Data_VarEnergyPrice_Grid1.csv
el1xr_opt/Grid1/oM_Data_VarFixedAvailability_Grid1.csv
el1xr_opt/Grid1/oM_Data_VarMaxConsumption_Grid1.csv
el1xr_opt/Grid1/oM_Data_VarMaxDemand_Grid1.csv
el1xr_opt/Grid1/oM_Data_VarMaxEmissionCost_Grid1.csv
el1xr_opt/Grid1/oM_Data_VarMaxEnergy_Grid1.csv
el1xr_opt/Grid1/oM_Data_VarMaxFuelCost_Grid1.csv
el1xr_opt/Grid1/oM_Data_VarMaxGeneration_Grid1.csv
el1xr_opt/Grid1/oM_Data_VarMaxInflows_Grid1.csv
el1xr_opt/Grid1/oM_Data_VarMaxOutflows_Grid1.csv
el1xr_opt/Grid1/oM_Data_VarMaxStorage_Grid1.csv
el1xr_opt/Grid1/oM_Data_VarMinConsumption_Grid1.csv
el1xr_opt/Grid1/oM_Data_VarMinDemand_Grid1.csv
el1xr_opt/Grid1/oM_Data_VarMinEmissionCost_Grid1.csv
el1xr_opt/Grid1/oM_Data_VarMinEnergy_Grid1.csv
el1xr_opt/Grid1/oM_Data_VarMinFuelCost_Grid1.csv
el1xr_opt/Grid1/oM_Data_VarMinGeneration_Grid1.csv
el1xr_opt/Grid1/oM_Data_VarMinInflows_Grid1.csv
el1xr_opt/Grid1/oM_Data_VarMinOutflows_Grid1.csv
el1xr_opt-1.0.13.dist-info/entry_points.txt
el1xr_opt-1.0.13.dist-info/licenses/LICENSE
el1xr_opt-1.0.13.dist-info/WHEEL
el1xr_opt-1.0.13.dist-info/METADATA
el1xr_opt-1.0.13.dist-info/RECORD
