Metadata-Version: 2.4
Name: el1xr_opt
Version: 1.0.13
Summary: An open-source optimization model for the design and operation of hybrid renewable energy systems with automatic solver setup
Author-email: EL1XR-dev Team <erik.alvarez@ri.se>
Requires-Python: >=3.11
Classifier: Development Status :: 5 - Production/Stable
Classifier: Intended Audience :: Science/Research
Classifier: License :: OSI Approved :: GNU General Public License v3 or later (GPLv3+)
Classifier: Operating System :: OS Independent
Classifier: Programming Language :: Python :: 3.11
Classifier: Programming Language :: Python :: 3.12
License-File: LICENSE
Requires-Dist: pyomo>=6.8.0
Requires-Dist: matplotlib>=3.3.4
Requires-Dist: numpy>=1.20.1
Requires-Dist: pandas>=1.2.3
Requires-Dist: plotly>=5.7.0
Requires-Dist: colour>=0.1.5
Requires-Dist: altair>=5.0.0
Requires-Dist: psutil>=5.8.0
Requires-Dist: jsonschema>=4.16.0
Requires-Dist: streamlit>=1.38.0
Requires-Dist: networkx>=3.3
Requires-Dist: ausankey>=1.5.0
Requires-Dist: amplpy>=0.15.0
Requires-Dist: duckdb>=1.2.2
Project-URL: Homepage, https://el1xr_opt.readthedocs.io/en/latest/index.html
Project-URL: Issues, https://github.com/EL1XR-dev/el1xr_opt/issues
Project-URL: Repository, https://github.com/EL1XR-dev/el1xr_opt
